[{
  "type": "flex",
  "altText": "ฟรี 100 กดสมัครเลย",
  "contents": {
  "type": "carousel",
  "contents": [
    {
      "type": "bubble",
      "hero": {
        "type": "image",
        "url": "https://img5.pic.in.th/file/secure-sv1/c028144dc7e7f6e7ecda9e22768b7e05.jpg",
        "size": "full",
        "action": {
          "type": "uri",
          "label": "action",
          "uri": "https://lin.ee/27q8Q4O"
        }
      },
      "body": {
        "type": "box",
        "layout": "vertical",
        "contents": [
          {
            "type": "text",
            "text": "สมัครชิกใหม่ฟรี 100 บาท",
            "align": "center",
            "weight": "bold",
            "size": "xl",
            "color": "#FFF5EE"
          },
          {
            "type": "text",
            "text": "กดปุ่มเขียวรับฟรี เครดิต",
            "align": "center",
            "size": "md",
            "color": "#FFF5EE",
            "weight": "bold"
          },
          {
            "type": "box",
            "layout": "horizontal",
            "contents": [
              {
                "type": "button",
                "action": {
                  "type": "uri",
                  "label": "รับเครดิตฟรี",
                  "uri": "https://lin.ee/27q8Q4O"
                },
                "style": "primary",
                "height": "sm",
                "margin": "md",
                "color": "#00CC00"
              }
            ],
            "margin": "lg"
          }
        ],
        "background": {
          "type": "linearGradient",
          "angle": "0deg",
          "startColor": "#000000",
          "endColor": "#000000",
          "centerColor": "#070042"
        },
        "action": {
          "type": "uri",
          "label": "action",
          "uri": "https://lin.ee/27q8Q4O"
        }
      }
    },
    {
      "type": "bubble",
      "hero": {
        "type": "image",
        "url": "https://img5.pic.in.th/file/secure-sv1/PCX--12--BETFLIXTIK.jpg",
        "size": "full",
        "action": {
          "type": "uri",
          "label": "action",
          "uri": "https://lin.ee/27q8Q4O"
        }
      },
      "body": {
        "type": "box",
        "layout": "vertical",
        "contents": [
          {
            "type": "text",
            "text": "แพ้ ชนะ",
            "align": "center",
            "size": "xl",
            "weight": "bold",
            "color": "#FFF5EE"
          },
          {
            "type": "text",
            "text": "12 ไม้ติด รับฟรั PCX",
            "align": "center",
            "weight": "bold",
            "size": "md",
            "color": "#FFF5EE"
          },
          {
            "type": "box",
            "layout": "horizontal",
            "contents": [
              {
                "type": "button",
                "action": {
                  "type": "uri",
                  "label": "เว็ปไซต์",
                  "uri": "https://lin.ee/nZANCZi"
                },
                "margin": "md",
                "height": "sm",
                "style": "primary",
                "color": "#00CC00"
              }
            ],
            "margin": "lg",
            "action": {
              "type": "uri",
              "label": "action",
              "uri": "https://lin.ee/27q8Q4O"
            }
          }
        ],
        "background": {
          "type": "linearGradient",
          "angle": "0deg",
          "startColor": "#000000",
          "endColor": "#000000",
          "centerColor": "#070042"
        },
        "action": {
          "type": "uri",
          "label": "action",
          "uri": "https://lin.ee/27q8Q4O"
        }
      }
    }
  ]
}
}]
