[{
  "type": "flex",
  "altText": "👉แจกหนักไม่ต้องฝากก่อน📌",
  "contents": {
  "type": "carousel",
  "contents": [
    {
      "type": "bubble",
      "hero": {
        "type": "image",
        "url": "https://cdn.pic.in.th/file/picinth/S__46743660.jpeg",
        "size": "full",
        "action": {
          "type": "uri",
          "label": "action",
          "uri": "https://lin.ee/28sCx5e"
        }
      },
      "body": {
        "type": "box",
        "layout": "vertical",
        "contents": [
          {
            "type": "text",
            "text": "ย้ำแจกฟรี💥 ทำยอด1,000",
            "align": "center",
            "weight": "bold",
            "size": "lg",
            "color": "#FF9900"
          },
          {
            "type": "text",
            "text": "ถอนได้สูงสุด 500 บาท",
            "align": "center",
            "size": "lg",
            "color": "#FF9900"
          },
          {
            "type": "box",
            "layout": "horizontal",
            "contents": [
              {
                "type": "button",
                "action": {
                  "type": "uri",
                  "label": "รับเครดิตฟรี",
                  "uri": "https://lin.ee/28sCx5e"
                },
                "style": "primary",
                "height": "sm",
                "margin": "md"
              },
              {
                "type": "button",
                "action": {
                  "type": "uri",
                  "label": "สมัคร",
                  "uri": "https://betflixautox168.com/"
                },
                "style": "primary",
                "height": "sm",
                "margin": "md"
              }
            ],
            "margin": "lg"
          }
        ],
        "background": {
          "type": "linearGradient",
          "angle": "0deg",
          "startColor": "#FF0000",
          "endColor": "#000000"
        }
      }
    }
  ]
}
}]
